cs2fade/AcidFadeCalculator.py
cs2fade/AmberFadeCalculator.py
cs2fade/BaseCalculator.py
cs2fade/FadeCalculator.py
cs2fade/Interfaces.py
cs2fade/RandomNumberGenerator.py
cs2fade/__init__.py
cs2fade-0.3.0.dist-info/METADATA
cs2fade-0.3.0.dist-info/WHEEL
cs2fade-0.3.0.dist-info/licenses/LICENSE
cs2fade-0.3.0.dist-info/RECORD
