Metadata-Version: 2.4
Name: cs2fade
Version: 0.3.0
Summary: CS2 fade utility
License: GPL-3.0-or-later
License-File: LICENSE
Author: Lukas Mahler
Author-email: m@hler.eu
Requires-Python: >=3.9,<4.0
Classifier: License :: OSI Approved :: GNU General Public License v3 (GPLv3)
Classifier: License :: OSI Approved :: GNU General Public License v3 or later (GPLv3+)
Classifier: Operating System :: OS Independent
Classifier: Programming Language :: Python :: 3
Classifier: Programming Language :: Python :: 3.9
Classifier: Programming Language :: Python :: 3.10
Classifier: Programming Language :: Python :: 3.11
Classifier: Programming Language :: Python :: 3.12
Classifier: Programming Language :: Python :: 3.13
Classifier: Programming Language :: Python :: 3.14
Project-URL: Repository, https://github.com/Helyux/cs2fade
